buildpipe/__init__.py
buildpipe/__main__.py
buildpipe-0.8.0.dist-info/LICENSE
buildpipe-0.8.0.dist-info/METADATA
buildpipe-0.8.0.dist-info/WHEEL
buildpipe-0.8.0.dist-info/entry_points.txt
buildpipe-0.8.0.dist-info/top_level.txt
buildpipe-0.8.0.dist-info/RECORD
