Metadata-Version: 2.1
Name: buildpipe
Version: 0.8.0
Summary: Dynamically generate Buildkite pipelines
Home-page: https://github.com/jwplayer/buildpipe-buildkite-plugin
Author: Kamil Sindi
Author-email: kamil@jwplayer.com
License: MIT
Keywords: pipeline,buildkite,buildkite-plugin,cicd
Platform: UNKNOWN
Classifier: Development Status :: 4 - Beta
Classifier: Intended Audience :: Developers
Classifier: License :: OSI Approved :: MIT License
Classifier: Environment :: Console
Classifier: Programming Language :: Python :: 3
Classifier: Programming Language :: Python :: 3.6
Classifier: Programming Language :: Python :: 3.7
Classifier: Programming Language :: Python :: 3.8
Requires-Dist: ruamel.yaml (>=0.16.10)
Requires-Dist: jsonschema (>=3.2.0)
Requires-Dist: setuptools-scm
